nbprint_example_plugin/__init__.py
nbprint_example_plugin/config/__init__.py
nbprint_example_plugin/config/nbprint/page/nbprint_example_plugin/default.yaml
nbprint_example_plugin/tests/test_all.py
nbprint_example_plugin-0.2.0.dist-info/METADATA
nbprint_example_plugin-0.2.0.dist-info/WHEEL
nbprint_example_plugin-0.2.0.dist-info/entry_points.txt
nbprint_example_plugin-0.2.0.dist-info/licenses/LICENSE
nbprint_example_plugin-0.2.0.dist-info/RECORD
